pytest_sqlguard/__init__.py
pytest_sqlguard/perf_rec.py
pytest_sqlguard/sql.py
pytest_sqlguard/sqlguard.py
pytest_sqlguard-2025.606.0.dist-info/METADATA
pytest_sqlguard-2025.606.0.dist-info/WHEEL
pytest_sqlguard-2025.606.0.dist-info/entry_points.txt
pytest_sqlguard-2025.606.0.dist-info/licenses/LICENSE
pytest_sqlguard-2025.606.0.dist-info/RECORD
