Metadata-Version: 2.4
Name: pytest-sqlguard
Version: 2025.606.0
Summary: Pytest fixture to record and check SQL Queries made by SQLAlchemy
Author-email: Manu <manuel.vives@paylead.fr>
License-Expression: MIT
License-File: LICENSE
Classifier: Development Status :: 4 - Beta
Classifier: Framework :: Pytest
Classifier: Intended Audience :: Developers
Classifier: License :: OSI Approved :: MIT License
Classifier: Programming Language :: Python :: 3.8
Classifier: Programming Language :: Python :: 3.9
Classifier: Programming Language :: Python :: 3.10
Classifier: Programming Language :: Python :: 3.11
Classifier: Programming Language :: Python :: 3.12
Classifier: Programming Language :: Python :: 3.13
Classifier: Programming Language :: SQL
Classifier: Topic :: Software Development :: Build Tools
Classifier: Topic :: Software Development :: Testing
Classifier: Topic :: Software Development :: Testing :: BDD
Requires-Python: >=3.8
Requires-Dist: filelock>=3
Requires-Dist: pytest>=7
Requires-Dist: pyyaml>=6.0.2
Requires-Dist: sqlalchemy>=2.0.31
Requires-Dist: sqlparse>=0.4
